cwinput/__init__.py
cwinput/binds.py
cwinput/main.py
cwinput-0.1.4.dist-info/LICENSE
cwinput-0.1.4.dist-info/METADATA
cwinput-0.1.4.dist-info/WHEEL
cwinput-0.1.4.dist-info/top_level.txt
cwinput-0.1.4.dist-info/RECORD
