Metadata-Version: 2.1
Name: cwinput
Version: 0.1.4
Summary: Listen to raw console input
Author: Zhilkaidarov Damir
Author-email: Zhilkaidarov Damir <rustam030201@gmail.com>
License: MIT License
Project-URL: Homepage, https://github.com/mitaraaa/cwinput
Classifier: Development Status :: 4 - Beta
Classifier: License :: OSI Approved :: MIT License
Classifier: Programming Language :: Python :: 3.10
Classifier: Programming Language :: Python :: 3.11
Requires-Python: >=3.10
License-File: LICENSE
